{"cameraMode":{"drawMode":0,"name":"Shaded","section":"Shading Mode"},"sceneLighting":false,"audioPlay":false,"sceneViewState":{"m_AlwaysRefresh":false,"showFog":true,"showSkybox":false,"showFlares":true,"showImageEffects":true,"showParticleSystems":true,"showVisualEffectGraphs":true,"m_FxEnabled":true},"in2DMode":false,"pivot":{"x":69.85038757324219,"y":144.27105712890626,"z":81.27135467529297},"rotation":{"x":-0.1426280438899994,"y":0.8560445308685303,"z":-0.3239785134792328,"w":-0.3767920136451721},"size":3.8091747760772707,"orthographic":false}